agimus/__init__.py
agimus/async_client.py
agimus/async_query.py
agimus/client.py
agimus/exceptions.py
agimus/py.typed
agimus/query.py
agimus-0.2.0.dist-info/METADATA
agimus-0.2.0.dist-info/WHEEL
agimus-0.2.0.dist-info/top_level.txt
agimus-0.2.0.dist-info/RECORD
